sistem/__init__.py
sistem/ancestry.py
sistem/parameters.py
sistem/anatomy/__init__.py
sistem/anatomy/base_anatomy.py
sistem/anatomy/genotype_anatomy.py
sistem/anatomy/static_anatomy.py
sistem/anatomy/utils.py
sistem/data/__init__.py
sistem/data/profiles.py
sistem/data/reads.py
sistem/data/sequence.py
sistem/data/summarize.py
sistem/data/utils.py
sistem/genome/__init__.py
sistem/genome/chromosome.py
sistem/genome/genome.py
sistem/genome/utils.py
sistem/lineage/__init__.py
sistem/lineage/cell.py
sistem/lineage/lineage.py
sistem/lineage/mutation.py
sistem/lineage/reevolve.py
sistem/lineage/tree.py
sistem/lineage/utils.py
sistem/selection/__init__.py
sistem/selection/arm_library.py
sistem/selection/base_library.py
sistem/selection/hybrid_library.py
sistem/selection/region_library.py
sistem/utilities/IO.py
sistem/utilities/__init__.py
sistem/utilities/utilities.py
sistem-1.0.4.dist-info/licenses/LICENSE
sistem-1.0.4.dist-info/METADATA
sistem-1.0.4.dist-info/WHEEL
sistem-1.0.4.dist-info/top_level.txt
sistem-1.0.4.dist-info/RECORD
