Metadata-Version: 2.4
Name: sistem
Version: 1.0.4
Summary: Genotype-driven tumor growth and metastasis simulator
Author: Samson Weiner
Author-email: Samson Weiner <samson.weiner@uconn.edu>
License:                     GNU GENERAL PUBLIC LICENSE
Project-URL: Homepage, https://github.com/samsonweiner/sistem
Requires-Python: >=3.9
License-File: LICENSE
Requires-Dist: numpy
Requires-Dist: scipy
Requires-Dist: scikit-learn
Requires-Dist: biopython
Requires-Dist: pyfaidx
Dynamic: license-file
